{
  "NotStatement": {
    "Statement": {
      "OrStatement": {
        "Statements": [
          {
            "AndStatement": {
              "Statements": [
                {
                  "ByteMatchStatement": {
                    "SearchString": "/remote.php/dav/",
                    "FieldToMatch": {
                      "UriPath": {}
                    },
                    "TextTransformations": [
                      {
                        "Priority": 0,
                        "Type": "NONE"
                      }
                    ],
                    "PositionalConstraint": "STARTS_WITH"
                  }
                },
                {
                  "ByteMatchStatement": {
                    "SearchString": "PROPFIND",
                    "FieldToMatch": {
                      "Method": {}
                    },
                    "TextTransformations": [
                      {
                        "Priority": 0,
                        "Type": "NONE"
                      }
                    ],
                    "PositionalConstraint": "EXACTLY"
                  }
                }
              ]
            }
          },
          {
            "AndStatement": {
              "Statements": [
                {
                  "ByteMatchStatement": {
                    "SearchString": "/apps/theming/",
                    "FieldToMatch": {
                      "UriPath": {}
                    },
                    "TextTransformations": [
                      {
                        "Priority": 0,
                        "Type": "NONE"
                      }
                    ],
                    "PositionalConstraint": "STARTS_WITH"
                  }
                },
                {
                  "ByteMatchStatement": {
                    "SearchString": "POST",
                    "FieldToMatch": {
                      "Method": {}
                    },
                    "TextTransformations": [
                      {
                        "Priority": 0,
                        "Type": "NONE"
                      }
                    ],
                    "PositionalConstraint": "EXACTLY"
                  }
                }
              ]
            }
          }
        ]
      }
    }
  }
}